clawpack-5.13.1.dist-info/METADATA
clawpack-5.13.1.dist-info/WHEEL
clawpack/pyclaw/classic/classic1.cpython-313-darwin.so
clawpack/pyclaw/classic/classic2.cpython-313-darwin.so
clawpack/pyclaw/classic/classic3.cpython-313-darwin.so
clawpack/pyclaw/classic/classic2_sw_sphere.cpython-313-darwin.so
clawpack/pyclaw/sharpclaw/sharpclaw1.cpython-313-darwin.so
clawpack/pyclaw/sharpclaw/sharpclaw2.cpython-313-darwin.so
clawpack/pyclaw/sharpclaw/sharpclaw3.cpython-313-darwin.so
clawpack/pyclaw/sharpclaw/euler_sharpclaw1.cpython-313-darwin.so
clawpack/pyclaw/sharpclaw/euler_tfluct1.cpython-313-darwin.so
clawpack/pyclaw/limiters/weno/reconstruct.cpython-313-darwin.so
clawpack/pyclaw/examples/shallow_sphere/sw_sphere_problem.cpython-313-darwin.so
clawpack/pyclaw/examples/advection_reaction_2d/advection_2d.cpython-313-darwin.so
clawpack/riemann/acoustics_1D_ptwise.cpython-313-darwin.so
clawpack/riemann/advection_1D_ptwise.cpython-313-darwin.so
clawpack/riemann/acoustics_2D_ptwise.cpython-313-darwin.so
clawpack/riemann/acoustics_1D.cpython-313-darwin.so
clawpack/riemann/acoustics_variable_1D.cpython-313-darwin.so
clawpack/riemann/advection_1D.cpython-313-darwin.so
clawpack/riemann/advection_color_1D.cpython-313-darwin.so
clawpack/riemann/burgers_1D.cpython-313-darwin.so
clawpack/riemann/cubic_1D.cpython-313-darwin.so
clawpack/riemann/traffic_1D.cpython-313-darwin.so
clawpack/riemann/traffic_vc_1D.cpython-313-darwin.so
clawpack/riemann/traffic_vc_fwave_1D.cpython-313-darwin.so
clawpack/riemann/traffic_vc_tracer_1D.cpython-313-darwin.so
clawpack/riemann/euler_with_efix_1D.cpython-313-darwin.so
clawpack/riemann/euler_hlle_1D.cpython-313-darwin.so
clawpack/riemann/mhd_roe_1D.cpython-313-darwin.so
clawpack/riemann/nonlinear_elasticity_fwave_1D.cpython-313-darwin.so
clawpack/riemann/psystem_fwave_1D.cpython-313-darwin.so
clawpack/riemann/reactive_euler_with_efix_1D.cpython-313-darwin.so
clawpack/riemann/shallow_hlle_1D.cpython-313-darwin.so
clawpack/riemann/shallow_roe_with_efix_1D.cpython-313-darwin.so
clawpack-5.13.1.dist-info/RECORD
