Metadata-Version: 2.1
Name: Clawpack
Version: 5.13.1
Summary: Finite volume methods for hyperbolic conservation laws
Keywords: scientific computing,numerical methods,partial differential equations
License: BSD-3-Clause
Classifier: Development Status :: 5 - Production/Stable
Classifier: Intended Audience :: Developers
Classifier: Intended Audience :: Science/Research
Classifier: License :: OSI Approved :: BSD License
Classifier: Operating System :: MacOS
Classifier: Operating System :: MacOS :: MacOS X
Classifier: Operating System :: POSIX
Classifier: Operating System :: POSIX :: BSD
Classifier: Operating System :: POSIX :: Linux
Classifier: Operating System :: Unix
Classifier: Programming Language :: C
Classifier: Programming Language :: Fortran
Classifier: Programming Language :: Python
Classifier: Programming Language :: Python :: 3
Classifier: Programming Language :: Python :: 3 :: Only
Classifier: Programming Language :: Python :: 3.6
Classifier: Programming Language :: Python :: 3.7
Classifier: Programming Language :: Python :: 3.8
Classifier: Programming Language :: Python :: 3.9
Classifier: Programming Language :: Python :: 3.10
Classifier: Programming Language :: Python :: 3.11
Classifier: Programming Language :: Python :: 3.12
Classifier: Topic :: Scientific/Engineering
Project-URL: Homepage, https://www.clawpack.org/
Project-URL: Documentation, https://www.clawpack.org/
Project-URL: Source, https://github.com/clawpack/
Project-URL: Issues, https://github.com/clawpack/clawpack/issues
Project-URL: Downloads, https://github.com/clawpack/clawpack/releases
Requires-Python: >=3.6
